{
  "game": "Vampire Savior",
  "character": "SASQUATCH",
  "movesList": [
    {
      "id": "sp_0",
      "name": "Big Breath",
      "type": "special",
      "input": "263P"
    },
    {
      "id": "sp_1",
      "name": "Big Typhoon",
      "type": "special",
      "input": "62[es2]3K"
    },
    {
      "id": "sp_2",
      "name": "Big Towers",
      "type": "special",
      "input": "22[es1]P"
    },
    {
      "id": "ex_0",
      "name": "Big Sledge",
      "type": "special",
      "input": "236236PP"
    },
    {
      "id": "ex_1",
      "name": "Big Freezer",
      "type": "special",
      "input": "236236KK"
    },
    {
      "id": "sp_0",
      "name": "Standing Light Punch",
      "type": "normal",
      "input": "LP"
    },
    {
      "id": "sp_1",
      "name": "Standing Medium Punch",
      "type": "normal",
      "input": "MP"
    },
    {
      "id": "sp_2",
      "name": "Standing Heavy Punch",
      "type": "normal",
      "input": "HP"
    },
    {
      "id": "sp_3",
      "name": "Standing Light Kick",
      "type": "normal",
      "input": "LK"
    },
    {
      "id": "sp_4",
      "name": "Standing Medium Kick",
      "type": "normal",
      "input": "MK"
    },
    {
      "id": "sp_5",
      "name": "Standing Heavy Kick",
      "type": "normal",
      "input": "HK"
    },
    {
      "id": "sp_6",
      "name": "Crouching Light Punch",
      "type": "normal",
      "input": "2LP"
    },
    {
      "id": "sp_7",
      "name": "Crouching Medium Punch",
      "type": "normal",
      "input": "2MP"
    },
    {
      "id": "sp_8",
      "name": "Crouching Heavy Punch",
      "type": "normal",
      "input": "2HP"
    },
    {
      "id": "sp_9",
      "name": "Crouching Light Kick",
      "type": "normal",
      "input": "2LK"
    },
    {
      "id": "sp_10",
      "name": "Crouching Medium Kick",
      "type": "normal",
      "input": "2MK"
    },
    {
      "id": "sp_11",
      "name": "Crouching Heavy Kick",
      "type": "normal",
      "input": "2HK"
    },
    {
      "id": "sp_12",
      "name": "Jumping Light Punch",
      "type": "normal",
      "input": "8LP"
    },
    {
      "id": "sp_13",
      "name": "Jumping Medium Punch",
      "type": "normal",
      "input": "8MP"
    },
    {
      "id": "sp_14",
      "name": "Jumping Heavy Punch",
      "type": "normal",
      "input": "8HP"
    },
    {
      "id": "sp_15",
      "name": "Jumping Light Kick",
      "type": "normal",
      "input": "8LK"
    },
    {
      "id": "sp_16",
      "name": "Jumping Medium Kick",
      "type": "normal",
      "input": "8MK"
    },
    {
      "id": "sp_17",
      "name": "Jumping Heavy Kick",
      "type": "normal",
      "input": "8HK"
    },
    {
      "id": "sp_20",
      "name": "Big Blow",
      "type": "special",
      "input": "623P"
    },
    {
      "id": "sp_22",
      "name": "SPECIAL THROW",
      "type": "throw",
      "input": "624fd1P"
    },
    {
      "id": "sp_23",
      "name": "SPECIAL THROW II",
      "type": "throw",
      "input": "[es6]360degK"
    },
    {
      "id": "sp_24",
      "name": "GUARD CANCEL",
      "type": "special",
      "input": "623K"
    },
    {
      "id": "sp_25",
      "name": "DARK FORCE",
      "type": "special",
      "input": "samestrengthPK"
    },
    {
      "id": "sp_26",
      "name": "Is",
      "type": "special",
      "input": "(lplk"
    }
  ],
  "combosList": []
}