{
  "game": "Dead or Alive",
  "character": "Ayane",
  "movesList": [
    {
      "id": "shoulder-throw",
      "name": "Shoulder Throw",
      "type": "special",
      "input": "ShoulderThrow"
    },
    {
      "id": "monkey-flip-toss",
      "name": "Monkey Flip Toss",
      "type": "special",
      "input": "MonkeyFlipToss"
    },
    {
      "id": "reverse-monkey-flip",
      "name": "Reverse Monkey Flip",
      "type": "special",
      "input": "ReverseMonkeyFlip"
    },
    {
      "id": "chest-dropkick",
      "name": "Chest Dropkick",
      "type": "special",
      "input": "ChestDropkick"
    },
    {
      "id": "slide-between-legs",
      "name": "Slide Between Legs",
      "type": "special",
      "input": "SlideBetweenLegs"
    },
    {
      "id": "hop-over-back",
      "name": "Hop Over Back",
      "type": "special",
      "input": "HopOverBack"
    },
    {
      "id": "twirling-punch",
      "name": "Twirling Punch",
      "type": "special",
      "input": "TwirlingPunch"
    },
    {
      "id": "balancing-act",
      "name": "Balancing Act",
      "type": "special",
      "input": "BalancingAct"
    },
    {
      "id": "chest-kick",
      "name": "Chest Kick",
      "type": "special",
      "input": "^!chestKick"
    },
    {
      "id": "rolling-arm-drag",
      "name": "Rolling Arm Drag",
      "type": "special",
      "input": "RollingArmDrag"
    },
    {
      "id": "flipover-powerbomb",
      "name": "Flipover Powerbomb",
      "type": "special",
      "input": "FlipoverPowerbomb"
    },
    {
      "id": "butt-slam",
      "name": "Butt Slam",
      "type": "special",
      "input": "^!buttSlam"
    },
    {
      "id": "twirling-punch",
      "name": "Twirling Punch",
      "type": "special",
      "input": "TwirlingPunch"
    },
    {
      "id": "twirling-punch",
      "name": "Twirling Punch",
      "type": "special",
      "input": "TwirlingPunch"
    },
    {
      "id": "twirling-punch",
      "name": "Twirling Punch",
      "type": "special",
      "input": "TwirlingPunch"
    },
    {
      "id": "high-leg-toss",
      "name": "High Leg Toss",
      "type": "special",
      "input": "HighLegToss"
    },
    {
      "id": "turn-around-bk",
      "name": "Turn Around: Bk",
      "type": "special",
      "input": "TurnAround:Bk"
    },
    {
      "id": "neck-breaker",
      "name": "Neck Breaker",
      "type": "special",
      "input": "NeckBreaker"
    },
    {
      "id": "n_0",
      "name": "Light Punch",
      "type": "normal",
      "input": "LP"
    },
    {
      "id": "n_1",
      "name": "Medium Punch",
      "type": "normal",
      "input": "MP"
    },
    {
      "id": "n_2",
      "name": "Heavy Punch",
      "type": "normal",
      "input": "HP"
    },
    {
      "id": "n_3",
      "name": "Light Kick",
      "type": "normal",
      "input": "LK"
    },
    {
      "id": "n_4",
      "name": "Medium Kick",
      "type": "normal",
      "input": "MK"
    },
    {
      "id": "n_5",
      "name": "Heavy Kick",
      "type": "normal",
      "input": "HK"
    },
    {
      "id": "t_0",
      "name": "Forward Throw",
      "type": "throw",
      "input": "LP+LK"
    },
    {
      "id": "t_1",
      "name": "Back Throw",
      "type": "throw",
      "input": "4LP+LK"
    }
  ]
}