{
  "game": "Art of Fighting 2",
  "character": "Temjin",
  "movesList": [
    {
      "name": "Uppercut",
      "type": "normal",
      "inputs": [
        "A+C"
      ],
      "id": "uppercut"
    },
    {
      "name": "Low Heavy Kick",
      "type": "normal",
      "inputs": [
        "B+C"
      ],
      "id": "low-heavy-kick"
    },
    {
      "name": "Moko Mouretsu Hasaidan",
      "type": "special",
      "inputs": [
        "down",
        "down-forward",
        "forward",
        "+A"
      ],
      "id": "moko-mouretsu-hasaidan"
    },
    {
      "name": "Tatsumaki Geki",
      "type": "special",
      "inputs": [
        "forward",
        "down",
        "down-forward",
        "+A"
      ],
      "id": "tatsumaki-geki"
    },
    {
      "name": "Kidan Heki",
      "type": "special",
      "inputs": [
        "down",
        "down-back",
        "back",
        "+A"
      ],
      "id": "kidan-heki"
    },
    {
      "name": "Mouko Rengeki Kenkyaku",
      "type": "special",
      "inputs": [
        "forward",
        "down-forward",
        "down",
        "down-back",
        "back",
        "+A",
        " ",
        "(",
        "Close",
        ")"
      ],
      "id": "mouko-rengeki-kenkyaku"
    },
    {
      "name": "Raigeki Dan",
      "type": "special",
      "inputs": [
        "forward",
        "down-forward",
        "down",
        "down-back",
        "back",
        "+B",
        " ",
        "(",
        "Close",
        ")"
      ],
      "id": "raigeki-dan"
    },
    {
      "name": "Mouko Temjin Ranbu",
      "type": "super",
      "inputs": [
        "down",
        "down-forward",
        "forward",
        "down-forward",
        "down",
        "down-back",
        "back",
        "+B"
      ],
      "id": "mouko-temjin-ranbu"
    }
  ]
}