{
    "game": "Street Fighter EX3",
    "character": "Skullomania",
    "movesList": [
        {
            "id": "sp_0",
            "name": "Skullo Dash",
            "type": "special",
            "inputs": [
                "down",
                "down-forward",
                "forward",
                "P"
            ]
        },
        {
            "id": "sp_1",
            "name": "Skullo Tackle",
            "type": "special",
            "inputs": [
                "6",
                "P (after Dash)"
            ]
        },
        {
            "id": "sp_2",
            "name": "Skullo Head",
            "type": "special",
            "inputs": [
                "forward",
                "down",
                "down-forward",
                "P"
            ]
        },
        {
            "id": "sp_3",
            "name": "Skullo Crusher",
            "type": "special",
            "inputs": [
                "down",
                "down-forward",
                "forward",
                "K"
            ]
        },
        {
            "id": "sp_4",
            "name": "Skullo Slider",
            "type": "special",
            "inputs": [
                "down",
                "down-back",
                "back",
                "K"
            ]
        }
    ],
    "combosList": []
}