{
  "game": "Capcom vs. SNK 2: Mark of the Millennium 2001",
  "character": "Kim Kaphwan",
  "movesList": [
    {
      "id": "sakkyakunage",
      "name": "Sakkyaku Nage",
      "type": "throw",
      "inputs": [
        "back",
        "or",
        "forward",
        "HP"
      ]
    },
    {
      "id": "rengekikyaku",
      "name": "Rengekikyaku",
      "type": "throw",
      "inputs": [
        "back",
        "or",
        "forward",
        "HK"
      ]
    },
    {
      "id": "nerichagi",
      "name": "Neri Chagi",
      "type": "normal",
      "inputs": [
        "forward",
        "HK"
      ]
    },
    {
      "id": "kamae",
      "name": "Kamae",
      "type": "normal",
      "inputs": [
        "_O",
        "HK"
      ]
    },
    {
      "id": "forwardmidkick",
      "name": "^!forward Mid Kick",
      "type": "normal",
      "inputs": [
        "LP"
      ]
    },
    {
      "id": "haishukyaku",
      "name": "^!haishukyaku",
      "type": "normal",
      "inputs": [
        "back",
        "or",
        "forward",
        "MP"
      ]
    },
    {
      "id": "haishikyaku",
      "name": "^!haishikyaku",
      "type": "normal",
      "inputs": [
        "HP"
      ]
    },
    {
      "id": "shidenkyaku",
      "name": "^!shiden Kyaku",
      "type": "normal",
      "inputs": [
        "LK"
      ]
    },
    {
      "id": "reversenerichagi",
      "name": "^!reverse Neri Chagi",
      "type": "normal",
      "inputs": [
        "MK"
      ]
    },
    {
      "id": "hangetsuzan",
      "name": "Hangetsu Zan",
      "type": "special",
      "inputs": [
        "down",
        "down-back",
        "back",
        "K"
      ]
    },
    {
      "id": "hienzan",
      "name": "Hien Zan",
      "type": "special",
      "inputs": [
        "^2",
        "up",
        "K"
      ]
    },
    {
      "id": "tenshouzanwithj",
      "name": "^!tenshou Zan (with ^j)",
      "type": "special",
      "inputs": [
        "down",
        "HK"
      ]
    },
    {
      "id": "kuusajin",
      "name": "Kuu Sajin",
      "type": "special",
      "inputs": [
        "^2",
        "up",
        "P"
      ]
    },
    {
      "id": "ryuuseiraku",
      "name": "Ryuusei Raku",
      "type": "special",
      "inputs": [
        "^4",
        "forward",
        "K"
      ]
    },
    {
      "id": "hakikyaku",
      "name": "Haki Kyaku",
      "type": "special",
      "inputs": [
        "down",
        "down",
        "K"
      ]
    },
    {
      "id": "hishoukyaku",
      "name": "Hishou Kyaku",
      "type": "special",
      "inputs": [
        "_^",
        "down",
        "down-forward",
        "forward",
        "K"
      ]
    }
  ],
  "combosList": []
}