{
  "name": "Strider Hiryu",
  "character": "Strider Hiryu",
  "game": "Marvel vs. Capcom: Infinite",
  "movesList": [
    {
      "id": "striderhiryu_4",
      "name": "Ame-no-Murakumo",
      "input": "236 + P",
      "type": "Special Moves"
    },
    {
      "id": "striderhiryu_5",
      "name": "Excalibur",
      "input": "236 + P or K",
      "type": "Special Moves",
      "notes": "Can only be used in air"
    },
    {
      "id": "striderhiryu_6",
      "name": "Wall Cling",
      "input": "236 + LK",
      "type": "Special Moves",
      "notes": "Varied follow-up"
    },
    {
      "id": "striderhiryu_7",
      "name": "> Cypher Lateral Strike",
      "input": "LP",
      "type": "Special Moves",
      "notes": "during Wall Cling"
    },
    {
      "id": "striderhiryu_8",
      "name": "> Raikiri Slash",
      "input": "HP",
      "type": "Special Moves",
      "notes": "during Wall Cling"
    },
    {
      "id": "striderhiryu_9",
      "name": "> Ladder Kick",
      "input": "LK",
      "type": "Special Moves",
      "notes": "during Wall Cling"
    },
    {
      "id": "striderhiryu_10",
      "name": "> Leaping Kick",
      "input": "HK",
      "type": "Special Moves",
      "notes": "during Wall Cling"
    },
    {
      "id": "striderhiryu_11",
      "name": "> Climb",
      "input": "8 /Hold 8",
      "type": "Special Moves",
      "notes": "during Wall Cling"
    },
    {
      "id": "striderhiryu_12",
      "name": "> Descend",
      "input": "2 /Hold 2",
      "type": "Special Moves",
      "notes": "during Wall Cling"
    },
    {
      "id": "striderhiryu_13",
      "name": "> Wall Exchange",
      "input": "4 + 6",
      "type": "Special Moves",
      "notes": "during Wall Cling"
    },
    {
      "id": "striderhiryu_14",
      "name": "> Dismount",
      "input": "6",
      "type": "Special Moves",
      "notes": "during Wall Cling"
    },
    {
      "id": "striderhiryu_15",
      "name": "Vajra",
      "input": "2 2 + P or K",
      "type": "Special Moves"
    },
    {
      "id": "striderhiryu_16",
      "name": "Gram",
      "input": "214 + P",
      "type": "Special Moves",
      "notes": "Can be used in air"
    },
    {
      "id": "striderhiryu_17",
      "name": "Formation C",
      "input": "214 + LK",
      "type": "Special Moves"
    },
    {
      "id": "striderhiryu_18",
      "name": "Formation B",
      "input": "214 + HK",
      "type": "Special Moves",
      "notes": "Can be followed up"
    },
    {
      "id": "striderhiryu_19",
      "name": "> Shot",
      "input": "214 + HK",
      "type": "Special Moves",
      "notes": "during Formation B"
    },
    {
      "id": "striderhiryu_21",
      "name": "Legion",
      "input": "236 + P P",
      "type": "Special Moves"
    },
    {
      "id": "striderhiryu_22",
      "name": "Brionac",
      "input": "236 + P P",
      "type": "Special Moves",
      "notes": "Can only be used in air"
    },
    {
      "id": "striderhiryu_23",
      "name": "Ouroboros",
      "input": "2 2 + K K",
      "type": "Special Moves"
    },
    {
      "id": "striderhiryu_24",
      "name": "Ragnarok (Level 3)",
      "input": "236 + K K",
      "type": "Special Moves"
    },
    {
      "id": "striderhiryu_26",
      "name": "Lateral Slice",
      "input": "6 + LP",
      "type": "Special Moves",
      "notes": "Can be used in air"
    },
    {
      "id": "striderhiryu_27",
      "name": "Arch Cut",
      "input": "3 + LK",
      "type": "Special Moves"
    },
    {
      "id": "striderhiryu_28",
      "name": "Formation A1",
      "input": "6 + HP",
      "type": "Special Moves"
    },
    {
      "id": "striderhiryu_29",
      "name": "Formation A2",
      "input": "6 + HK",
      "type": "Special Moves"
    },
    {
      "id": "striderhiryu_30",
      "name": "Slide",
      "input": "3 + HK",
      "type": "Special Moves"
    }
  ]
}