{
  "name": "Chin Wo",
  "character": "Chin Wo",
  "game": "Eternal Champions",
  "movesList": [
    {
      "name": "Healing",
      "input": "236X",
      "type": "common"
    },
    {
      "name": "Radial Fire",
      "input": "214Y",
      "type": "common"
    },
    {
      "name": "Focus Ball",
      "input": "46Z",
      "type": "common"
    },
    {
      "name": "Slide Kick",
      "input": "46C",
      "type": "common"
    },
    {
      "name": "Flying Kick",
      "input": "236B",
      "type": "common"
    },
    {
      "name": "Acupuncture Pin",
      "input": "46A",
      "type": "common"
    }
  ]
}