{
  "name": "Radel",
  "character": "Radel",
  "game": "Rage of the Dragons",
  "movesList": [
    {
      "name": "Leg cyclone",
      "input": "4 or 6C",
      "type": "throw"
    },
    {
      "name": "Double spike",
      "input": "3B",
      "type": "normal"
    },
    {
      "name": "Glass escape",
      "input": "236P",
      "type": "special"
    },
    {
      "name": "Dead dragon",
      "input": "623P",
      "type": "special"
    },
    {
      "name": "Screw back",
      "input": "63214K",
      "type": "special"
    },
    {
      "name": "Head execution",
      "input": "close63214P",
      "type": "special"
    },
    {
      "name": "^!glass smash",
      "input": "214P",
      "type": "special"
    }
  ]
}