{
    "game": "roster",
    "character": "Krizalid (Boss)",
    "movesList": [
        {
            "id": "sp_0",
            "name": "Typhon Rage",
            "type": "special",
            "inputs": [
                "down",
                "down-forward",
                "forward",
                "P"
            ]
        },
        {
            "id": "sp_1",
            "name": "Rising Dark",
            "type": "special",
            "inputs": [
                "forward",
                "down",
                "down-forward",
                "P"
            ]
        },
        {
            "id": "sp_2",
            "name": "Desperate Moment",
            "type": "special",
            "inputs": [
                "forward",
                "down-forward",
                "down",
                "down-back",
                "back",
                "P"
            ]
        }
    ],
    "combosList": []
}