{
  "game": "Zero Divide",
  "character": "Tau",
  "movesList": [
    {
      "name": "Smashing Tail Strike",
      "inputs": [
        "43K"
      ],
      "id": "smashing-tail-strike"
    },
    {
      "name": "Move and Strike",
      "inputs": [
        "226K"
      ],
      "id": "move-and-strike"
    },
    {
      "name": "Helicopter Spin",
      "inputs": [
        "426P+K"
      ],
      "id": "helicopter-spin"
    },
    {
      "name": "Tau Driver",
      "inputs": [
        "360P"
      ],
      "id": "tau-driver"
    },
    {
      "name": "Power Bomb",
      "inputs": [
        "41236P"
      ],
      "id": "power-bomb"
    },
    {
      "name": "Hammer Combo",
      "inputs": [
        "PP6P6P"
      ],
      "id": "hammer-combo"
    },
    {
      "name": "Stomp Combo",
      "inputs": [
        "KK"
      ],
      "id": "stomp-combo"
    },
    {
      "name": "Tail Strike",
      "inputs": [
        "4K"
      ],
      "id": "tail-strike"
    }
  ]
}