{
  "game": "The King of Fighters: Maximum Impact 2 (KOF 2006)",
  "character": "Billy Kane",
  "movesList": [
    {
      "id": "sup_0",
      "name": "Chou Kaen Senpuu Kon",
      "type": "super",
      "inputs": [
        "down",
        "down-forward",
        "forward",
        "down-forward",
        "down",
        "down-back",
        "back",
        "A/C"
      ]
    },
    {
      "id": "sup_1",
      "name": "Dai Senpuu",
      "type": "super",
      "inputs": [
        "down",
        "down-forward",
        "forward",
        "down",
        "down-forward",
        "forward",
        "A/C"
      ]
    },
    {
      "id": "sp_2",
      "name": "Sansetsu Kon: Chuudan Uchi",
      "type": "special",
      "inputs": [
        "back",
        "down-back",
        "down",
        "down-forward",
        "forward",
        "A/C"
      ]
    },
    {
      "id": "sp_3",
      "name": "Senpuu Kon",
      "type": "special",
      "inputs": [
        "Tap A/C rapidly"
      ]
    },
    {
      "id": "sp_4",
      "name": "Suzume Otoshi",
      "type": "special",
      "inputs": [
        "down",
        "down-back",
        "back",
        "A/C"
      ]
    },
    {
      "id": "sp_5",
      "name": "Kyoushuu Hishou Kon",
      "type": "special",
      "inputs": [
        "forward",
        "down",
        "down-forward",
        "B/D"
      ]
    }
  ],
  "combosList": []
}