{
  "name": "Harley Quinn",
  "character": "Harley Quinn",
  "game": "Injustice: Gods Among Us",
  "movesList": [
    {
      "name": "Pop Pop",
      "input": "241",
      "type": "Special"
    },
    {
      "name": "Line of Fire",
      "input": "261",
      "type": "Special"
    },
    {
      "name": "Play Doctor",
      "input": "242",
      "type": "Special"
    },
    {
      "name": "Cupcake Bomb",
      "input": "462",
      "type": "Special"
    },
    {
      "name": "Mallet Smash",
      "input": "1+2+3",
      "type": "Super"
    },
    {
      "id": "n_0",
      "name": "Front Punch",
      "type": "normal",
      "input": "1"
    },
    {
      "id": "n_1",
      "name": "Back Punch",
      "type": "normal",
      "input": "2"
    },
    {
      "id": "n_2",
      "name": "Front Kick",
      "type": "normal",
      "input": "3"
    },
    {
      "id": "n_3",
      "name": "Back Kick",
      "type": "normal",
      "input": "4"
    },
    {
      "id": "t_0",
      "name": "Forward Throw",
      "type": "throw",
      "input": "1+3"
    },
    {
      "id": "t_1",
      "name": "Back Throw",
      "type": "throw",
      "input": "41+3"
    }
  ]
}