{
  "game": "Tatsunoko vs. Capcom: Ultimate All-Stars",
  "character": "Ryu",
  "movesList": [
    {
      "id": "sp_0",
      "name": "Hadouken",
      "type": "special",
      "inputs": [
        "down",
        "down-forward",
        "forward",
        "Attack (Air OK)"
      ]
    },
    {
      "id": "sp_1",
      "name": "Shoryuken",
      "type": "special",
      "inputs": [
        "forward",
        "down",
        "down-forward",
        "Attack (Air OK)"
      ]
    },
    {
      "id": "sp_2",
      "name": "Tatsumaki Senpukyaku",
      "type": "special",
      "inputs": [
        "down",
        "down-back",
        "back",
        "Attack (Air OK)"
      ]
    },
    {
      "id": "sup_0",
      "name": "Shinku Hadouken",
      "type": "super",
      "inputs": [
        "down",
        "down-forward",
        "forward",
        "AT (Air OK)"
      ]
    },
    {
      "id": "sup_1",
      "name": "Shinku Tatsumaki Senpukyaku",
      "type": "super",
      "inputs": [
        "down",
        "down-back",
        "back",
        "AT"
      ]
    },
    {
      "id": "sup_2",
      "name": "Shin Shoryuken",
      "type": "super",
      "inputs": [
        "forward",
        "down",
        "down-forward",
        "AT",
        " ",
        "(",
        "Level",
        " ",
        "down-forward",
        ")"
      ]
    }
  ],
  "combosList": []
}