[
  {"name":"Patriotic Punch","input":"1","type":"normal"},
  {"name":"Smash Hit","input":"1 2","type":"string"},
  {"name":"Rise of a Hero","input":"1 2 1","type":"string"},
  {"name":"Battering Ram","input":"b 1","type":"normal"},
  {"name":"Enforcing Order","input":"b 1 4","type":"string"},
  {"name":"Heroic De-Escalation","input":"b 1 4 2","type":"string"},
  {"name":"Backhand","input":"2","type":"normal"},
  {"name":"Backhanded Praise","input":"b 2 2","type":"string"},
  {"name":"Piercing Gaze","input":"f 2 1","type":"string"},
  {"name":"Back to Earth","input":"f 2 1 1","type":"string"},
  {"name":"If Looks Could Kill","input":"f 2 1 1+4","type":"string"},
  {"name":"Knee","input":"3","type":"normal"},
  {"name":"Roundhouse","input":"4","type":"normal"},
  {"name":"Poke","input":"d 1","type":"normal"},
  {"name":"Uppercut","input":"d 2","type":"normal"},
  {"name":"Low Kick","input":"d 3","type":"normal"},
  {"name":"Sweep","input":"d 4","type":"normal"},
  {"name":"Air Punch","input":"j 1","type":"normal","notes":"Air"},
  {"name":"Air Slam","input":"j 2","type":"normal","notes":"Air"},
  {"name":"Air Kick","input":"j 3","type":"normal","notes":"Air"},
  {"name":"Air Roundhouse","input":"j 4","type":"normal","notes":"Air"},
  {"name":"Laser Eyes","input":"b f 2","type":"special"},
  {"name":"Dirty Trick","input":"d b 3","type":"special"},
  {"name":"Diabolical Dash","input":"b f 4","type":"special"},
  {"name":"Rising High","input":"d b 4","type":"special"},
  {"name":"Flight","input":"u u b","type":"special"},
  {"name":"Forward Throw","input":"1+3","type":"throw"},
  {"name":"Back Throw","input":"b 1+3","type":"throw"},
  {"name":"Fatal Blow","input":"EN+BL","type":"special"},
  {"name":"Fatality 1 (Laser Show)","input":"d f d 2 (Mid)","type":"finisher"},
  {"name":"Fatality 2 (You Are Beneath Me)","input":"b f b 4 (Close)","type":"finisher"},
  {"name":"Animality","input":"d d b 1 (Mid)","type":"finisher"}
]
