{
  "name": "Fernandez",
  "character": "Fernandez",
  "game": "Waku Waku 7",
  "movesList": [
    {
      "name": "Fernand-Beam",
      "input": "236P",
      "type": "special"
    },
    {
      "name": "Fernand-Breath",
      "input": "214P",
      "type": "special"
    },
    {
      "name": "Fernand-Rising",
      "input": "623P",
      "type": "special"
    },
    {
      "name": "Fernand-Crush",
      "input": "63214K",
      "type": "special"
    },
    {
      "name": "Hara Hara: Fernand-Storm",
      "input": "22PP",
      "type": "hara hara"
    },
    {
      "name": "Doki Doki: Fernand-Galaxy",
      "input": "236236P",
      "type": "doki doki"
    }
  ]
}